fading/__init__.py
fading/audiofading.py
audiofadingMarcos-0.0.1.dist-info/LICENSE
audiofadingMarcos-0.0.1.dist-info/METADATA
audiofadingMarcos-0.0.1.dist-info/WHEEL
audiofadingMarcos-0.0.1.dist-info/top_level.txt
audiofadingMarcos-0.0.1.dist-info/RECORD
