Metadata-Version: 2.1
Name: audiofadingMarcos
Version: 0.0.1
Summary: efeitofadingmarcos
Home-page: https://github.com/ghist
Author: Marcos
License: UNKNOWN
Platform: UNKNOWN
Classifier: Programming Language :: Python :: 3
Classifier: License :: OSI Approved :: MIT License
Classifier: Operating System :: OS Independent
Requires-Python: >=3.6
License-File: LICENSE
